[
  {
    "@id": "http://example.com/keyword_ID",
    "@type": [
      "http://www.w3.org/1999/02/22-rdf-syntax-ns#Property"
    ],
    "http://www.w3.org/2000/01/rdf-schema#domain": [
      {
        "@id": "http://example.com/Keyword"
      }
    ],
    "http://www.w3.org/2000/01/rdf-schema#range": [
      {
        "@id": "http://www.w3.org/2001/XMLSchema#string"
      }
    ]
  },
  {
    "@id": "http://example.com/work_publicationId",
    "@type": [
      "http://www.w3.org/1999/02/22-rdf-syntax-ns#Property"
    ],
    "http://www.w3.org/2000/01/rdf-schema#domain": [
      {
        "@id": "http://example.com/Workshop"
      }
    ],
    "http://www.w3.org/2000/01/rdf-schema#range": [
      {
        "@id": "http://www.w3.org/2001/XMLSchema#string"
      }
    ]
  },
  {
    "@id": "http://example.com/Event",
    "@type": [
      "http://www.w3.org/2000/01/rdf-schema#Class"
    ],
    "http://www.w3.org/2000/01/rdf-schema#subClassOf": [
      {
        "@id": "http://example.com/Publication"
      }
    ]
  },
  {
    "@id": "http://example.com/Establishment",
    "@type": [
      "http://www.w3.org/2000/01/rdf-schema#Class"
    ]
  },
  {
    "@id": "http://example.com/work_venue",
    "@type": [
      "http://www.w3.org/1999/02/22-rdf-syntax-ns#Property"
    ],
    "http://www.w3.org/2000/01/rdf-schema#domain": [
      {
        "@id": "http://example.com/Workshop"
      }
    ],
    "http://www.w3.org/2000/01/rdf-schema#range": [
      {
        "@id": "http://www.w3.org/2001/XMLSchema#string"
      }
    ]
  },
  {
    "@id": "http://example.com/conf_name",
    "@type": [
      "http://www.w3.org/1999/02/22-rdf-syntax-ns#Property"
    ],
    "http://www.w3.org/2000/01/rdf-schema#domain": [
      {
        "@id": "http://example.com/Conference"
      }
    ],
    "http://www.w3.org/2000/01/rdf-schema#range": [
      {
        "@id": "http://www.w3.org/2001/XMLSchema#string"
      }
    ]
  },
  {
    "@id": "http://example.com/jour_issn",
    "@type": [
      "http://www.w3.org/1999/02/22-rdf-syntax-ns#Property"
    ],
    "http://www.w3.org/2000/01/rdf-schema#domain": [
      {
        "@id": "http://example.com/Journal"
      }
    ],
    "http://www.w3.org/2000/01/rdf-schema#range": [
      {
        "@id": "http://www.w3.org/2001/XMLSchema#integer"
      }
    ]
  },
  {
    "@id": "http://example.com/conf_publicationId",
    "@type": [
      "http://www.w3.org/1999/02/22-rdf-syntax-ns#Property"
    ],
    "http://www.w3.org/2000/01/rdf-schema#domain": [
      {
        "@id": "http://example.com/Conference"
      }
    ],
    "http://www.w3.org/2000/01/rdf-schema#range": [
      {
        "@id": "http://www.w3.org/2001/XMLSchema#string"
      }
    ]
  },
  {
    "@id": "http://example.com/writes",
    "@type": [
      "http://www.w3.org/1999/02/22-rdf-syntax-ns#Property"
    ],
    "http://www.w3.org/2000/01/rdf-schema#domain": [
      {
        "@id": "http://example.com/Author"
      }
    ],
    "http://www.w3.org/2000/01/rdf-schema#range": [
      {
        "@id": "http://example.com/Paper"
      }
    ]
  },
  {
    "@id": "http://example.com/reviewerId",
    "@type": [
      "http://www.w3.org/1999/02/22-rdf-syntax-ns#Property"
    ],
    "http://www.w3.org/2000/01/rdf-schema#domain": [
      {
        "@id": "http://example.com/Reviewer"
      }
    ],
    "http://www.w3.org/2000/01/rdf-schema#range": [
      {
        "@id": "http://www.w3.org/2001/XMLSchema#string"
      }
    ]
  },
  {
    "@id": "http://example.com/work_year",
    "@type": [
      "http://www.w3.org/1999/02/22-rdf-syntax-ns#Property"
    ],
    "http://www.w3.org/2000/01/rdf-schema#domain": [
      {
        "@id": "http://example.com/Workshop"
      }
    ],
    "http://www.w3.org/2000/01/rdf-schema#range": [
      {
        "@id": "http://www.w3.org/2001/XMLSchema#integer"
      }
    ]
  },
  {
    "@id": "http://example.com/conf_venue",
    "@type": [
      "http://www.w3.org/1999/02/22-rdf-syntax-ns#Property"
    ],
    "http://www.w3.org/2000/01/rdf-schema#domain": [
      {
        "@id": "http://example.com/Conference"
      }
    ],
    "http://www.w3.org/2000/01/rdf-schema#range": [
      {
        "@id": "http://www.w3.org/2001/XMLSchema#string"
      }
    ]
  },
  {
    "@id": "http://example.com/Organization",
    "@type": [
      "http://www.w3.org/2000/01/rdf-schema#Class"
    ],
    "http://www.w3.org/2000/01/rdf-schema#subClassOf": [
      {
        "@id": "http://example.com/Establishment"
      }
    ]
  },
  {
    "@id": "http://example.com/Work_Proceedings",
    "@type": [
      "http://www.w3.org/2000/01/rdf-schema#Class"
    ]
  },
  {
    "@id": "http://example.com/cites",
    "@type": [
      "http://www.w3.org/1999/02/22-rdf-syntax-ns#Property"
    ],
    "http://www.w3.org/2000/01/rdf-schema#domain": [
      {
        "@id": "http://example.com/Paper"
      }
    ],
    "http://www.w3.org/2000/01/rdf-schema#range": [
      {
        "@id": "http://example.com/Paper"
      }
    ]
  },
  {
    "@id": "http://example.com/conf_edition",
    "@type": [
      "http://www.w3.org/1999/02/22-rdf-syntax-ns#Property"
    ],
    "http://www.w3.org/2000/01/rdf-schema#domain": [
      {
        "@id": "http://example.com/Conference"
      }
    ],
    "http://www.w3.org/2000/01/rdf-schema#range": [
      {
        "@id": "http://www.w3.org/2001/XMLSchema#integer"
      }
    ]
  },
  {
    "@id": "http://example.com/volume_year",
    "@type": [
      "http://www.w3.org/1999/02/22-rdf-syntax-ns#Property"
    ],
    "http://www.w3.org/2000/01/rdf-schema#domain": [
      {
        "@id": "http://example.com/Volume"
      }
    ],
    "http://www.w3.org/2000/01/rdf-schema#range": [
      {
        "@id": "http://www.w3.org/2001/XMLSchema#integer"
      }
    ]
  },
  {
    "@id": "http://example.com/assignReviewer",
    "@type": [
      "http://www.w3.org/1999/02/22-rdf-syntax-ns#Property"
    ],
    "http://www.w3.org/2000/01/rdf-schema#domain": [
      {
        "@id": "http://example.com/CommitteeMember"
      }
    ],
    "http://www.w3.org/2000/01/rdf-schema#range": [
      {
        "@id": "http://example.com/Reviewer"
      }
    ]
  },
  {
    "@id": "http://example.com/author_department",
    "@type": [
      "http://www.w3.org/1999/02/22-rdf-syntax-ns#Property"
    ],
    "http://www.w3.org/2000/01/rdf-schema#domain": [
      {
        "@id": "http://example.com/Author"
      }
    ],
    "http://www.w3.org/2000/01/rdf-schema#range": [
      {
        "@id": "http://www.w3.org/2001/XMLSchema#string"
      }
    ]
  },
  {
    "@id": "http://example.com/Conference",
    "@type": [
      "http://www.w3.org/2000/01/rdf-schema#Class"
    ],
    "http://www.w3.org/2000/01/rdf-schema#subClassOf": [
      {
        "@id": "http://example.com/Event"
      }
    ]
  },
  {
    "@id": "http://example.com/jour_year",
    "@type": [
      "http://www.w3.org/1999/02/22-rdf-syntax-ns#Property"
    ],
    "http://www.w3.org/2000/01/rdf-schema#domain": [
      {
        "@id": "http://example.com/Journal"
      }
    ],
    "http://www.w3.org/2000/01/rdf-schema#range": [
      {
        "@id": "http://www.w3.org/2001/XMLSchema#integer"
      }
    ]
  },
  {
    "@id": "http://example.com/author_name",
    "@type": [
      "http://www.w3.org/1999/02/22-rdf-syntax-ns#Property"
    ],
    "http://www.w3.org/2000/01/rdf-schema#domain": [
      {
        "@id": "http://example.com/Author"
      }
    ],
    "http://www.w3.org/2000/01/rdf-schema#range": [
      {
        "@id": "http://www.w3.org/2001/XMLSchema#string"
      }
    ]
  },
  {
    "@id": "http://example.com/majorityDecision",
    "@type": [
      "http://www.w3.org/1999/02/22-rdf-syntax-ns#Property"
    ],
    "http://www.w3.org/2000/01/rdf-schema#domain": [
      {
        "@id": "http://example.com/Reviewer"
      }
    ],
    "http://www.w3.org/2000/01/rdf-schema#range": [
      {
        "@id": "http://www.w3.org/2001/XMLSchema#string"
      }
    ]
  },
  {
    "@id": "http://example.com/Author",
    "@type": [
      "http://www.w3.org/2000/01/rdf-schema#Class"
    ],
    "http://www.w3.org/2000/01/rdf-schema#subClassOf": [
      {
        "@id": "http://example.com/Person"
      }
    ]
  },
  {
    "@id": "http://example.com/paperPartOfconf",
    "@type": [
      "http://www.w3.org/1999/02/22-rdf-syntax-ns#Property"
    ],
    "http://www.w3.org/2000/01/rdf-schema#domain": [
      {
        "@id": "http://example.com/Paper"
      }
    ],
    "http://www.w3.org/2000/01/rdf-schema#range": [
      {
        "@id": "http://example.com/Conf_Proceedings"
      }
    ]
  },
  {
    "@id": "http://example.com/Publication",
    "@type": [
      "http://www.w3.org/2000/01/rdf-schema#Class"
    ]
  },
  {
    "@id": "http://example.com/conf_url",
    "@type": [
      "http://www.w3.org/1999/02/22-rdf-syntax-ns#Property"
    ],
    "http://www.w3.org/2000/01/rdf-schema#domain": [
      {
        "@id": "http://example.com/Conference"
      }
    ],
    "http://www.w3.org/2000/01/rdf-schema#range": [
      {
        "@id": "http://www.w3.org/2001/XMLSchema#string"
      }
    ]
  },
  {
    "@id": "http://example.com/Conf_Proceedings_year",
    "@type": [
      "http://www.w3.org/1999/02/22-rdf-syntax-ns#Property"
    ],
    "http://www.w3.org/2000/01/rdf-schema#domain": [
      {
        "@id": "http://example.com/Conf_Proceedings"
      }
    ],
    "http://www.w3.org/2000/01/rdf-schema#range": [
      {
        "@id": "http://www.w3.org/2001/XMLSchema#integer"
      }
    ]
  },
  {
    "@id": "http://example.com/keyword_name",
    "@type": [
      "http://www.w3.org/1999/02/22-rdf-syntax-ns#Property"
    ],
    "http://www.w3.org/2000/01/rdf-schema#domain": [
      {
        "@id": "http://example.com/Keyword"
      }
    ],
    "http://www.w3.org/2000/01/rdf-schema#range": [
      {
        "@id": "http://www.w3.org/2001/XMLSchema#string"
      }
    ]
  },
  {
    "@id": "http://example.com/paper_title",
    "@type": [
      "http://www.w3.org/1999/02/22-rdf-syntax-ns#Property"
    ],
    "http://www.w3.org/2000/01/rdf-schema#domain": [
      {
        "@id": "http://example.com/Paper"
      }
    ],
    "http://www.w3.org/2000/01/rdf-schema#range": [
      {
        "@id": "http://www.w3.org/2001/XMLSchema#string"
      }
    ]
  },
  {
    "@id": "http://example.com/jour_publicationId",
    "@type": [
      "http://www.w3.org/1999/02/22-rdf-syntax-ns#Property"
    ],
    "http://www.w3.org/2000/01/rdf-schema#domain": [
      {
        "@id": "http://example.com/Journal"
      }
    ],
    "http://www.w3.org/2000/01/rdf-schema#range": [
      {
        "@id": "http://www.w3.org/2001/XMLSchema#string"
      }
    ]
  },
  {
    "@id": "http://example.com/paper_date",
    "@type": [
      "http://www.w3.org/1999/02/22-rdf-syntax-ns#Property"
    ],
    "http://www.w3.org/2000/01/rdf-schema#domain": [
      {
        "@id": "http://example.com/Paper"
      }
    ],
    "http://www.w3.org/2000/01/rdf-schema#range": [
      {
        "@id": "http://www.w3.org/2001/XMLSchema#date"
      }
    ]
  },
  {
    "@id": "http://example.com/presentedIn",
    "@type": [
      "http://www.w3.org/1999/02/22-rdf-syntax-ns#Property"
    ],
    "http://www.w3.org/2000/01/rdf-schema#domain": [
      {
        "@id": "http://example.com/Conf_Proceedings"
      }
    ],
    "http://www.w3.org/2000/01/rdf-schema#range": [
      {
        "@id": "http://example.com/Conference"
      }
    ]
  },
  {
    "@id": "http://example.com/decision",
    "@type": [
      "http://www.w3.org/1999/02/22-rdf-syntax-ns#Property"
    ],
    "http://www.w3.org/2000/01/rdf-schema#domain": [
      {
        "@id": "http://example.com/Reviewer"
      }
    ],
    "http://www.w3.org/2000/01/rdf-schema#range": [
      {
        "@id": "http://www.w3.org/2001/XMLSchema#string"
      }
    ]
  },
  {
    "@id": "http://example.com/paperId",
    "@type": [
      "http://www.w3.org/1999/02/22-rdf-syntax-ns#Property"
    ],
    "http://www.w3.org/2000/01/rdf-schema#domain": [
      {
        "@id": "http://example.com/Paper"
      }
    ],
    "http://www.w3.org/2000/01/rdf-schema#range": [
      {
        "@id": "http://www.w3.org/2001/XMLSchema#string"
      }
    ]
  },
  {
    "@id": "http://example.com/Keyword",
    "@type": [
      "http://www.w3.org/2000/01/rdf-schema#Class"
    ]
  },
  {
    "@id": "http://example.com/affiliatedWith",
    "@type": [
      "http://www.w3.org/1999/02/22-rdf-syntax-ns#Property"
    ],
    "http://www.w3.org/2000/01/rdf-schema#domain": [
      {
        "@id": "http://example.com/Author"
      }
    ],
    "http://www.w3.org/2000/01/rdf-schema#range": [
      {
        "@id": "http://example.com/Organization"
      }
    ]
  },
  {
    "@id": "http://example.com/domain",
    "@type": [
      "http://www.w3.org/1999/02/22-rdf-syntax-ns#Property"
    ],
    "http://www.w3.org/2000/01/rdf-schema#domain": [
      {
        "@id": "http://example.com/Keyword"
      }
    ],
    "http://www.w3.org/2000/01/rdf-schema#range": [
      {
        "@id": "http://www.w3.org/2001/XMLSchema#string"
      }
    ]
  },
  {
    "@id": "http://example.com/hasKeyword",
    "@type": [
      "http://www.w3.org/1999/02/22-rdf-syntax-ns#Property"
    ],
    "http://www.w3.org/2000/01/rdf-schema#domain": [
      {
        "@id": "http://example.com/Paper"
      }
    ],
    "http://www.w3.org/2000/01/rdf-schema#range": [
      {
        "@id": "http://example.com/Keyword"
      }
    ]
  },
  {
    "@id": "http://example.com/paper_link",
    "@type": [
      "http://www.w3.org/1999/02/22-rdf-syntax-ns#Property"
    ],
    "http://www.w3.org/2000/01/rdf-schema#domain": [
      {
        "@id": "http://example.com/Paper"
      }
    ],
    "http://www.w3.org/2000/01/rdf-schema#range": [
      {
        "@id": "http://www.w3.org/2001/XMLSchema#string"
      }
    ]
  },
  {
    "@id": "http://example.com/reviewContent",
    "@type": [
      "http://www.w3.org/1999/02/22-rdf-syntax-ns#Property"
    ],
    "http://www.w3.org/2000/01/rdf-schema#domain": [
      {
        "@id": "http://example.com/Reviewer"
      }
    ],
    "http://www.w3.org/2000/01/rdf-schema#range": [
      {
        "@id": "http://www.w3.org/2001/XMLSchema#string"
      }
    ]
  },
  {
    "@id": "http://example.com/Conf_Proceedings",
    "@type": [
      "http://www.w3.org/2000/01/rdf-schema#Class"
    ]
  },
  {
    "@id": "http://example.com/OrganizationID",
    "@type": [
      "http://www.w3.org/1999/02/22-rdf-syntax-ns#Property"
    ],
    "http://www.w3.org/2000/01/rdf-schema#domain": [
      {
        "@id": "http://example.com/Organization"
      }
    ],
    "http://www.w3.org/2000/01/rdf-schema#range": [
      {
        "@id": "http://www.w3.org/2001/XMLSchema#string"
      }
    ]
  },
  {
    "@id": "http://example.com/authorId",
    "@type": [
      "http://www.w3.org/1999/02/22-rdf-syntax-ns#Property"
    ],
    "http://www.w3.org/2000/01/rdf-schema#domain": [
      {
        "@id": "http://example.com/Author"
      }
    ],
    "http://www.w3.org/2000/01/rdf-schema#range": [
      {
        "@id": "http://www.w3.org/2001/XMLSchema#string"
      }
    ]
  },
  {
    "@id": "http://example.com/DOI",
    "@type": [
      "http://www.w3.org/1999/02/22-rdf-syntax-ns#Property"
    ],
    "http://www.w3.org/2000/01/rdf-schema#domain": [
      {
        "@id": "http://example.com/Paper"
      }
    ],
    "http://www.w3.org/2000/01/rdf-schema#range": [
      {
        "@id": "http://www.w3.org/2001/XMLSchema#string"
      }
    ]
  },
  {
    "@id": "http://example.com/Volume",
    "@type": [
      "http://www.w3.org/2000/01/rdf-schema#Class"
    ],
    "http://www.w3.org/2000/01/rdf-schema#subClassOf": [
      {
        "@id": "http://example.com/Publication"
      }
    ]
  },
  {
    "@id": "http://example.com/work_edition",
    "@type": [
      "http://www.w3.org/1999/02/22-rdf-syntax-ns#Property"
    ],
    "http://www.w3.org/2000/01/rdf-schema#domain": [
      {
        "@id": "http://example.com/Workshop"
      }
    ],
    "http://www.w3.org/2000/01/rdf-schema#range": [
      {
        "@id": "http://www.w3.org/2001/XMLSchema#integer"
      }
    ]
  },
  {
    "@id": "http://example.com/work_issn",
    "@type": [
      "http://www.w3.org/1999/02/22-rdf-syntax-ns#Property"
    ],
    "http://www.w3.org/2000/01/rdf-schema#domain": [
      {
        "@id": "http://example.com/Workshop"
      }
    ],
    "http://www.w3.org/2000/01/rdf-schema#range": [
      {
        "@id": "http://www.w3.org/2001/XMLSchema#integer"
      }
    ]
  },
  {
    "@id": "http://example.com/work_Proceedings_year",
    "@type": [
      "http://www.w3.org/1999/02/22-rdf-syntax-ns#Property"
    ],
    "http://www.w3.org/2000/01/rdf-schema#domain": [
      {
        "@id": "http://example.com/Work_Proceedings"
      }
    ],
    "http://www.w3.org/2000/01/rdf-schema#range": [
      {
        "@id": "http://www.w3.org/2001/XMLSchema#integer"
      }
    ]
  },
  {
    "@id": "http://example.com/publishedIn",
    "@type": [
      "http://www.w3.org/1999/02/22-rdf-syntax-ns#Property"
    ],
    "http://www.w3.org/2000/01/rdf-schema#domain": [
      {
        "@id": "http://example.com/Volume"
      }
    ],
    "http://www.w3.org/2000/01/rdf-schema#range": [
      {
        "@id": "http://example.com/Journal"
      }
    ]
  },
  {
    "@id": "http://example.com/paper_pages",
    "@type": [
      "http://www.w3.org/1999/02/22-rdf-syntax-ns#Property"
    ],
    "http://www.w3.org/2000/01/rdf-schema#domain": [
      {
        "@id": "http://example.com/Paper"
      }
    ],
    "http://www.w3.org/2000/01/rdf-schema#range": [
      {
        "@id": "http://www.w3.org/2001/XMLSchema#string"
      }
    ]
  },
  {
    "@id": "http://example.com/conf_issn",
    "@type": [
      "http://www.w3.org/1999/02/22-rdf-syntax-ns#Property"
    ],
    "http://www.w3.org/2000/01/rdf-schema#domain": [
      {
        "@id": "http://example.com/Conference"
      }
    ],
    "http://www.w3.org/2000/01/rdf-schema#range": [
      {
        "@id": "http://www.w3.org/2001/XMLSchema#integer"
      }
    ]
  },
  {
    "@id": "http://example.com/paperPartOfwork",
    "@type": [
      "http://www.w3.org/1999/02/22-rdf-syntax-ns#Property"
    ],
    "http://www.w3.org/2000/01/rdf-schema#domain": [
      {
        "@id": "http://example.com/Paper"
      }
    ],
    "http://www.w3.org/2000/01/rdf-schema#range": [
      {
        "@id": "http://example.com/Work_Proceedings"
      }
    ]
  },
  {
    "@id": "http://example.com/abstract",
    "@type": [
      "http://www.w3.org/1999/02/22-rdf-syntax-ns#Property"
    ],
    "http://www.w3.org/2000/01/rdf-schema#domain": [
      {
        "@id": "http://example.com/Paper"
      }
    ],
    "http://www.w3.org/2000/01/rdf-schema#range": [
      {
        "@id": "http://www.w3.org/2001/XMLSchema#string"
      }
    ]
  },
  {
    "@id": "http://example.com/jour_venue",
    "@type": [
      "http://www.w3.org/1999/02/22-rdf-syntax-ns#Property"
    ],
    "http://www.w3.org/2000/01/rdf-schema#domain": [
      {
        "@id": "http://example.com/Journal"
      }
    ],
    "http://www.w3.org/2000/01/rdf-schema#range": [
      {
        "@id": "http://www.w3.org/2001/XMLSchema#string"
      }
    ]
  },
  {
    "@id": "http://example.com/jour_name",
    "@type": [
      "http://www.w3.org/1999/02/22-rdf-syntax-ns#Property"
    ],
    "http://www.w3.org/2000/01/rdf-schema#domain": [
      {
        "@id": "http://example.com/Journal"
      }
    ],
    "http://www.w3.org/2000/01/rdf-schema#range": [
      {
        "@id": "http://www.w3.org/2001/XMLSchema#string"
      }
    ]
  },
  {
    "@id": "http://example.com/author_email",
    "@type": [
      "http://www.w3.org/1999/02/22-rdf-syntax-ns#Property"
    ],
    "http://www.w3.org/2000/01/rdf-schema#domain": [
      {
        "@id": "http://example.com/Author"
      }
    ],
    "http://www.w3.org/2000/01/rdf-schema#range": [
      {
        "@id": "http://www.w3.org/2001/XMLSchema#string"
      }
    ]
  },
  {
    "@id": "http://example.com/affiliationType",
    "@type": [
      "http://www.w3.org/1999/02/22-rdf-syntax-ns#Property"
    ],
    "http://www.w3.org/2000/01/rdf-schema#domain": [
      {
        "@id": "http://example.com/Organization"
      }
    ],
    "http://www.w3.org/2000/01/rdf-schema#range": [
      {
        "@id": "http://www.w3.org/2001/XMLSchema#string"
      }
    ]
  },
  {
    "@id": "http://example.com/Person",
    "@type": [
      "http://www.w3.org/2000/01/rdf-schema#Class"
    ]
  },
  {
    "@id": "http://example.com/reviews",
    "@type": [
      "http://www.w3.org/1999/02/22-rdf-syntax-ns#Property"
    ],
    "http://www.w3.org/2000/01/rdf-schema#domain": [
      {
        "@id": "http://example.com/Reviewer"
      }
    ],
    "http://www.w3.org/2000/01/rdf-schema#range": [
      {
        "@id": "http://example.com/Paper"
      }
    ]
  },
  {
    "@id": "http://example.com/Workshop",
    "@type": [
      "http://www.w3.org/2000/01/rdf-schema#Class"
    ],
    "http://www.w3.org/2000/01/rdf-schema#subClassOf": [
      {
        "@id": "http://example.com/Event"
      }
    ]
  },
  {
    "@id": "http://example.com/work_url",
    "@type": [
      "http://www.w3.org/1999/02/22-rdf-syntax-ns#Property"
    ],
    "http://www.w3.org/2000/01/rdf-schema#domain": [
      {
        "@id": "http://example.com/Workshop"
      }
    ],
    "http://www.w3.org/2000/01/rdf-schema#range": [
      {
        "@id": "http://www.w3.org/2001/XMLSchema#string"
      }
    ]
  },
  {
    "@id": "http://example.com/Reviewer",
    "@type": [
      "http://www.w3.org/2000/01/rdf-schema#Class"
    ],
    "http://www.w3.org/2000/01/rdf-schema#subClassOf": [
      {
        "@id": "http://example.com/Author"
      }
    ]
  },
  {
    "@id": "http://example.com/Paper",
    "@type": [
      "http://www.w3.org/2000/01/rdf-schema#Class"
    ],
    "http://www.w3.org/2000/01/rdf-schema#subClassOf": [
      {
        "@id": "http://example.com/Publication"
      }
    ]
  },
  {
    "@id": "http://example.com/correspondingAuthor",
    "@type": [
      "http://www.w3.org/1999/02/22-rdf-syntax-ns#Property"
    ],
    "http://www.w3.org/2000/01/rdf-schema#domain": [
      {
        "@id": "http://example.com/Author"
      }
    ],
    "http://www.w3.org/2000/01/rdf-schema#range": [
      {
        "@id": "http://example.com/Paper"
      }
    ]
  },
  {
    "@id": "http://example.com/citationCount",
    "@type": [
      "http://www.w3.org/1999/02/22-rdf-syntax-ns#Property"
    ],
    "http://www.w3.org/2000/01/rdf-schema#domain": [
      {
        "@id": "http://example.com/Paper"
      }
    ],
    "http://www.w3.org/2000/01/rdf-schema#range": [
      {
        "@id": "http://www.w3.org/2001/XMLSchema#integer"
      }
    ]
  },
  {
    "@id": "http://example.com/Journal",
    "@type": [
      "http://www.w3.org/2000/01/rdf-schema#Class"
    ]
  },
  {
    "@id": "http://example.com/paperPartOfjour",
    "@type": [
      "http://www.w3.org/1999/02/22-rdf-syntax-ns#Property"
    ],
    "http://www.w3.org/2000/01/rdf-schema#domain": [
      {
        "@id": "http://example.com/Paper"
      }
    ],
    "http://www.w3.org/2000/01/rdf-schema#range": [
      {
        "@id": "http://example.com/Volume"
      }
    ]
  },
  {
    "@id": "http://example.com/presentedInWork",
    "@type": [
      "http://www.w3.org/1999/02/22-rdf-syntax-ns#Property"
    ],
    "http://www.w3.org/2000/01/rdf-schema#domain": [
      {
        "@id": "http://example.com/Work_Proceedings"
      }
    ],
    "http://www.w3.org/2000/01/rdf-schema#range": [
      {
        "@id": "http://example.com/Workshop"
      }
    ]
  },
  {
    "@id": "http://example.com/conf_year",
    "@type": [
      "http://www.w3.org/1999/02/22-rdf-syntax-ns#Property"
    ],
    "http://www.w3.org/2000/01/rdf-schema#domain": [
      {
        "@id": "http://example.com/Conference"
      }
    ],
    "http://www.w3.org/2000/01/rdf-schema#range": [
      {
        "@id": "http://www.w3.org/2001/XMLSchema#integer"
      }
    ]
  },
  {
    "@id": "http://example.com/jour_url",
    "@type": [
      "http://www.w3.org/1999/02/22-rdf-syntax-ns#Property"
    ],
    "http://www.w3.org/2000/01/rdf-schema#domain": [
      {
        "@id": "http://example.com/Journal"
      }
    ],
    "http://www.w3.org/2000/01/rdf-schema#range": [
      {
        "@id": "http://www.w3.org/2001/XMLSchema#string"
      }
    ]
  },
  {
    "@id": "http://example.com/work_name",
    "@type": [
      "http://www.w3.org/1999/02/22-rdf-syntax-ns#Property"
    ],
    "http://www.w3.org/2000/01/rdf-schema#domain": [
      {
        "@id": "http://example.com/Workshop"
      }
    ],
    "http://www.w3.org/2000/01/rdf-schema#range": [
      {
        "@id": "http://www.w3.org/2001/XMLSchema#string"
      }
    ]
  },
  {
    "@id": "http://example.com/CommitteeMember",
    "@type": [
      "http://www.w3.org/2000/01/rdf-schema#Class"
    ]
  },
  {
    "@id": "http://example.com/affiliation_name",
    "@type": [
      "http://www.w3.org/1999/02/22-rdf-syntax-ns#Property"
    ],
    "http://www.w3.org/2000/01/rdf-schema#domain": [
      {
        "@id": "http://example.com/Organization"
      }
    ],
    "http://www.w3.org/2000/01/rdf-schema#range": [
      {
        "@id": "http://www.w3.org/2001/XMLSchema#string"
      }
    ]
  },
  {
    "@id": "http://example.com/publicationType",
    "@type": [
      "http://www.w3.org/1999/02/22-rdf-syntax-ns#Property"
    ],
    "http://www.w3.org/2000/01/rdf-schema#domain": [
      {
        "@id": "http://example.com/Journal"
      }
    ],
    "http://www.w3.org/2000/01/rdf-schema#range": [
      {
        "@id": "http://www.w3.org/2001/XMLSchema#string"
      }
    ]
  }
]